riverit_vesikanta_manager/__init__.py
riverit_vesikanta_manager/config_model.py
riverit_vesikanta_manager/constants.py
riverit_vesikanta_manager/form_model.py
riverit_vesikanta_manager/vesikanta_manager.py
riverit_vesikanta_manager-0.2.0.dist-info/METADATA
riverit_vesikanta_manager-0.2.0.dist-info/WHEEL
riverit_vesikanta_manager-0.2.0.dist-info/licenses/LICENSE
riverit_vesikanta_manager-0.2.0.dist-info/RECORD
