Metadata-Version: 2.3
Name: riverit-vesikanta-manager
Version: 0.2.0
Summary: Manager for Vesikanta operations
Author-email: Jukka-Pekka Haapaniemi <jp.haapaniemi@riverit.fi>
License:                                  Apache License
License-File: LICENSE
Classifier: Development Status :: 4 - Beta
Classifier: Intended Audience :: Developers
Classifier: Operating System :: Microsoft :: Windows
Classifier: Programming Language :: Python :: 3
Classifier: Topic :: Software Development :: Libraries
Requires-Python: >=3.10
Requires-Dist: email-validator>=2.2.0
Requires-Dist: pandas>=2.2.3
Requires-Dist: pyautogui>=0.9.54
Requires-Dist: pydantic>=2.9.2
Requires-Dist: robocorp-windows>=1.0.4
Requires-Dist: robocorp>=2.1.0
